<schemalist>
    <enum id="io.elementary.camera.settings.mode">
        <value nick="photo" value="0" />
        <value nick="video" value="1" />
    </enum>
    <schema path="/io/elementary/camera/settings/" id="io.elementary.camera.settings">
        <key name="mode" enum="io.elementary.camera.settings.mode">
            <default>"photo"</default>
            <summary>The mode of the camera, photo or video</summary>
            <description>Photo mode is represented by 0, video mode by 1</description>
        </key>
    </schema>
</schemalist>
